[{"title":"Elements","created":"2021-12-12T00:00:00.000Z","tags":["Urara","Elements"],"updated":"2024-08-20T03:24:53.038Z","images":[],"slug":"/hello-world/elements/+page.svelte.md","path":"/hello-world/elements","toc":[{"depth":2,"title":"Headings","slug":"headings"},{"depth":3,"title":"Heading","slug":"heading"},{"depth":4,"title":"Heading","slug":"heading-1"},{"depth":5,"title":"Heading","slug":"heading-2"},{"depth":6,"title":"Heading","slug":"heading-3"},{"depth":2,"title":"Paragraphs","slug":"paragraphs"},{"depth":2,"title":"Lists","slug":"lists"},{"depth":3,"title":"Definition List (dl)","slug":"definition-list-dl"},{"depth":3,"title":"Ordered List (ol)","slug":"ordered-list-ol"},{"depth":3,"title":"Unordered List (ul)","slug":"unordered-list-ul"},{"depth":3,"title":"Checkbox List (ul)","slug":"checkbox-list-ul"},{"depth":2,"title":"Table","slug":"table"},{"depth":2,"title":"Footnotes","slug":"footnotes"},{"depth":2,"title":"Code","slug":"code"},{"depth":2,"title":"Misc","slug":"misc"},{"depth":2,"title":"Svelte Components","slug":"svelte-components"}],"type":"article","html":""},{"title":"ToC Disabled","summary":"This post has disabled table of contents.","created":"2021-12-12T00:00:00.000Z","tags":["Front-Matter"],"toc":false,"updated":"2024-08-20T03:24:53.038Z","images":[],"slug":"/hello-world/toc-disabled/+page.md","path":"/hello-world/toc-disabled","type":"article","html":""},{"title":"Hello World","image":"/hello-world/urara.webp","alt":"Urara","created":"2021-11-01T00:00:00.000Z","updated":"2021-12-12T00:00:00.000Z","tags":["Hello World","Urara"],"images":[],"slug":"/hello-world/+page.svelte.md","path":"/hello-world","toc":[{"depth":2,"title":"Developing","slug":"developing"},{"depth":2,"title":"Building","slug":"building"},{"depth":2,"title":"Documentation","slug":"documentation"}],"type":"article","html":""}]